jlab_html_extension/__init__.py
jlab_html_extension/_version.py
jlab_html_extension-0.1.0.data/data/share/jupyter/labextensions/jlab_html_extension/build_log.json
jlab_html_extension-0.1.0.data/data/share/jupyter/labextensions/jlab_html_extension/package.json
jlab_html_extension-0.1.0.data/data/share/jupyter/labextensions/jlab_html_extension/static/lib_index_js.9901b9bcea409f79b3e6.js
jlab_html_extension-0.1.0.data/data/share/jupyter/labextensions/jlab_html_extension/static/lib_index_js.9901b9bcea409f79b3e6.js.map
jlab_html_extension-0.1.0.data/data/share/jupyter/labextensions/jlab_html_extension/static/remoteEntry.3772c0320be21248cfc4.js
jlab_html_extension-0.1.0.data/data/share/jupyter/labextensions/jlab_html_extension/static/remoteEntry.3772c0320be21248cfc4.js.map
jlab_html_extension-0.1.0.data/data/share/jupyter/labextensions/jlab_html_extension/static/style.js
jlab_html_extension-0.1.0.data/data/share/jupyter/labextensions/jlab_html_extension/static/style_index_js.7fcb970f16636f3a44be.js
jlab_html_extension-0.1.0.data/data/share/jupyter/labextensions/jlab_html_extension/static/style_index_js.7fcb970f16636f3a44be.js.map
jlab_html_extension-0.1.0.data/data/share/jupyter/labextensions/jlab_html_extension/install.json
jlab_html_extension-0.1.0.dist-info/METADATA
jlab_html_extension-0.1.0.dist-info/WHEEL
jlab_html_extension-0.1.0.dist-info/licenses/LICENSE
jlab_html_extension-0.1.0.dist-info/RECORD
