Metadata-Version: 2.3
Name: jlab_html_extension
Version: 0.1.0
Summary: Jupyter Lab extension to ease creating web pages.
Project-URL: Homepage, https://github.com/ICTSoEasy/jlab_html_extension
Project-URL: Bug Tracker, https://github.com/ICTSoEasy/jlab_html_extension/issues
Project-URL: Repository, https://github.com/ICTSoEasy/jlab_html_extension.git
Author-email: Oli Howson <oli.howson@open.ac.uk>
License: BSD 3-Clause License
License-File: LICENSE
Keywords: jupyter,jupyterlab,jupyterlab-extension
Classifier: Framework :: Jupyter
Classifier: Framework :: Jupyter :: JupyterLab
Classifier: Framework :: Jupyter :: JupyterLab :: 4
Classifier: Framework :: Jupyter :: JupyterLab :: Extensions
Classifier: Framework :: Jupyter :: JupyterLab :: Extensions :: Prebuilt
Classifier: License :: OSI Approved :: BSD License
Classifier: Programming Language :: Python
Classifier: Programming Language :: Python :: 3
Classifier: Programming Language :: Python :: 3.8
Classifier: Programming Language :: Python :: 3.9
Classifier: Programming Language :: Python :: 3.10
Classifier: Programming Language :: Python :: 3.11
Classifier: Programming Language :: Python :: 3.12
Requires-Python: >=3.8
